wrighter_plugins/__init__.py
wrighter_plugins/json_scraper.py
wrighter_plugins/network_logger.py
wrighter_plugins/page_timeout.py
wrighter_plugins/resource_blocker.py
wrighter_plugins/stealth_async.py
wrighter_plugins/stealth_sync.py
wrighter_plugins-0.0.2.dist-info/LICENSE
wrighter_plugins-0.0.2.dist-info/METADATA
wrighter_plugins-0.0.2.dist-info/WHEEL
wrighter_plugins-0.0.2.dist-info/top_level.txt
wrighter_plugins-0.0.2.dist-info/RECORD
