Metadata-Version: 2.1
Name: wrighter-plugins
Version: 0.0.2
Summary: Plugins for Wrighter
Author-email: Žiga Ivanšek <ziga.ivansek@gmail.com>
Project-URL: Repository, https://github.com/zigai/wrighter-plugins
Keywords: wrighter,plugins,wrighter plugins,playwright plugins,web scraping,browser automation plugins,JSON scraper,resource blocker,playwright stealth
Classifier: Programming Language :: Python
Classifier: Programming Language :: Python :: 3.10
Classifier: Programming Language :: Python :: 3 :: Only
Classifier: Topic :: Software Development :: Libraries :: Python Modules
Classifier: Topic :: Software Development :: Testing
Classifier: Topic :: Internet :: WWW/HTTP :: Browsers
Classifier: Intended Audience :: Developers
Classifier: License :: OSI Approved
Classifier: License :: OSI Approved :: MIT License
Classifier: Operating System :: OS Independent
Requires-Python: >=3.10
License-File: LICENSE
Requires-Dist: wrighter (==0.1.2)
Requires-Dist: stdl (>=0.4.4)
Requires-Dist: jsonschema (==4.17.3)
Requires-Dist: jsonpath-ng (==1.5.3)
Requires-Dist: playwright (>=1.29.0)
Provides-Extra: dev
Requires-Dist: black ; extra == 'dev'
Requires-Dist: pytest ; extra == 'dev'
Requires-Dist: flake8 ; extra == 'dev'
Provides-Extra: test
Requires-Dist: pytest ; extra == 'test'
